__init__.py
app_manager.py
utils.py
hp_uia_core-0.1.9.dist-info/METADATA
hp_uia_core-0.1.9.dist-info/WHEEL
hp_uia_core-0.1.9.dist-info/top_level.txt
hp_uia_core-0.1.9.dist-info/RECORD
