Metadata-Version: 2.4
Name: hp-uia-core
Version: 0.1.9
Summary: HP UI Automation Core Library for Windows application testing and validation
Author-email: HP PC Validation Team <iverson.lu@hp.com>
License: MIT
Project-URL: Homepage, https://github.com/hp-internal/hp-uia-core
Project-URL: Documentation, https://github.com/hp-internal/hp-uia-core#readme
Keywords: hp,ui automation,testing,windows,pywinauto,uia
Classifier: Development Status :: 4 - Beta
Classifier: Intended Audience :: Developers
Classifier: Programming Language :: Python :: 3
Classifier: Programming Language :: Python :: 3.13
Classifier: Operating System :: Microsoft :: Windows
Classifier: License :: OSI Approved :: MIT License
Classifier: Topic :: Software Development :: Testing
Requires-Python: >=3.13
Requires-Dist: psutil>=7.1.3
Requires-Dist: pywinauto>=0.6.9
Requires-Dist: wmi>=1.5.1
